{
	"info": {
		"_postman_id": "a9cfeca8-0f0a-4123-9f2a-ce3cc78c3592",
		"name": "Tier",
		"schema": "https://schema.getpostman.com/json/collection/v2.1.0/collection.json",
		"_exporter_id": "16214296"
	},
	"item": [
		{
			"name": "Create URL",
			"request": {
				"method": "POST",
				"header": [],
				"body": {
					"mode": "raw",
					"raw": "{\n    \"originalUrl\": \"https://www.npmjs.com/package/nanoid\"\n}",
					"options": {
						"raw": {
							"language": "json"
						}
					}
				},
				"url": {
					"raw": "http://localhost:3009/api/url",
					"protocol": "http",
					"host": [
						"localhost"
					],
					"port": "3009",
					"path": [
						"api",
						"url"
					]
				}
			},
			"response": []
		},
		{
			"name": "Original URL",
			"request": {
				"method": "GET",
				"header": [],
				"url": {
					"raw": "http://localhost:3009/api/url/4m7nN53zXt",
					"protocol": "http",
					"host": [
						"localhost"
					],
					"port": "3009",
					"path": [
						"api",
						"url",
						"4m7nN53zXt"
					]
				}
			},
			"response": []
		}
	]
}